[
  {
    "id": "bff509ff-9067-4922-8a82-6477facc9c5f",
    "name": "Pranay Test",
    "description": "A testing phase",
    "category": "Education",
    "url": "https://www.pornpics.com/",
    "image": "https://cdni.pornpics.com/1280/7/32/26678511/26678511_032_2edd.jpg",
    "pricing": "free",
    "features": [],
    "tags": [
      "Test\r\n            close",
      "Testing\r\n            close"
    ],
    "rating": 0,
    "date_added": "2025-07-22",
    "submitter": {
      "name": "Pranay",
      "email": "ypranaykumar1002@gmail.com"
    },
    "approved": true,
    "updated_at": "2025-07-22T05:50:06.906Z"
  }
]